README.txt
setup.py
collective/__init__.py
collective.cmfeditionsdexteritycompat.egg-info/PKG-INFO
collective.cmfeditionsdexteritycompat.egg-info/SOURCES.txt
collective.cmfeditionsdexteritycompat.egg-info/dependency_links.txt
collective.cmfeditionsdexteritycompat.egg-info/entry_points.txt
collective.cmfeditionsdexteritycompat.egg-info/namespace_packages.txt
collective.cmfeditionsdexteritycompat.egg-info/not-zip-safe
collective.cmfeditionsdexteritycompat.egg-info/requires.txt
collective.cmfeditionsdexteritycompat.egg-info/top_level.txt
collective/cmfeditionsdexteritycompat/README.txt
collective/cmfeditionsdexteritycompat/__init__.py
collective/cmfeditionsdexteritycompat/config.py
collective/cmfeditionsdexteritycompat/configure.zcml
collective/cmfeditionsdexteritycompat/profiles.zcml
collective/cmfeditionsdexteritycompat/setuphandlers.py
collective/cmfeditionsdexteritycompat/testing.py
collective/cmfeditionsdexteritycompat/browser/__init__.py
collective/cmfeditionsdexteritycompat/browser/configure.zcml
collective/cmfeditionsdexteritycompat/browser/containercontentcore.pt
collective/cmfeditionsdexteritycompat/browser/itemcontentcore.pt
collective/cmfeditionsdexteritycompat/browser/views.py
collective/cmfeditionsdexteritycompat/profiles/default/collective.cmfeditionsdexteritycompat_various.txt
collective/cmfeditionsdexteritycompat/profiles/default/metadata.xml
collective/cmfeditionsdexteritycompat/profiles/default/skins.xml
collective/cmfeditionsdexteritycompat/skins/collective_cmfeditionsdexteritycompat/get_macros_wrapper.py
collective/cmfeditionsdexteritycompat/skins/collective_cmfeditionsdexteritycompat/versions_history_form.pt
collective/cmfeditionsdexteritycompat/skins/collective_cmfeditionsdexteritycompat/versions_history_form.pt.metadata
collective/cmfeditionsdexteritycompat/tests/__init__.py
collective/cmfeditionsdexteritycompat/tests/configure.zcml
collective/cmfeditionsdexteritycompat/tests/test_functional.py
collective/cmfeditionsdexteritycompat/tests/test_install.py
docs/HISTORY.txt