Metadata-Version: 1.0
Name: collective.cmfeditionsdexteritycompat
Version: 0.1b8
Summary: Makes `Products.CMFEditions`_ works with `Dexterity` content types.
Home-page: http://
Author: Rafael Oliveira
Author-email: rafaelbco@gmail.com
License: ''
Platform: UNKNOWN
Classifier: Framework :: Plone
Classifier: Programming Language :: Python
Classifier: Topic :: Software Development :: Libraries :: Python Modules
